__init__.py
decorator/__init__.py
decorator/timeit.py
dto/__init__.py
dto/result.py
exception/__init__.py
exception/not_found_entity_error.py
model/__init__.py
model/audited_model.py
model/base_model.py
schema/__init__.py
schema/base_schema.py
wa_common-0.0.1.dist-info/METADATA
wa_common-0.0.1.dist-info/WHEEL
wa_common-0.0.1.dist-info/top_level.txt
wa_common-0.0.1.dist-info/RECORD
