Metadata-Version: 2.1
Name: wa-common
Version: 0.0.1
Classifier: Programming Language :: Python :: 3
Classifier: License :: OSI Approved :: MIT License
Classifier: Operating System :: OS Independent
Requires-Python: >=3.9
